LICENSE.txt
MANIFEST.in
README.md
requirements.txt
setup.cfg
setup.py
bin/methinks-env
bin/today
bin/today-python
config/config.yaml
methinks/__init__.py
methinks/api.py
methinks/config.py
methinks/db.py
methinks/parse.py
methinks/section.py
methinks/utils.py
methinks.egg-info/PKG-INFO
methinks.egg-info/SOURCES.txt
methinks.egg-info/dependency_links.txt
methinks.egg-info/requires.txt
methinks.egg-info/top_level.txt