Metadata-Version: 1.2
Name: methinks
Version: 0.0.2
Summary: Keep track of your reading, your todos and your notes. Whatever thinketh you.
Home-page: UNKNOWN
Author: Andreas Grivas
Author-email: andreasgrv@gmail.com
License: BSD
Download-URL: https://github.com/andreasgrv/methinks/archive/0.0.2.tar.gz
Keywords: self reporting
Platform: UNKNOWN
Requires-Python: >=3.6
